BMI_module.py
BMI_module/BMI_module.py
BMI_module-0.0.0.2.dist-info/METADATA
BMI_module-0.0.0.2.dist-info/WHEEL
BMI_module-0.0.0.2.dist-info/top_level.txt
BMI_module-0.0.0.2.dist-info/RECORD
